anna_tasks/__init__.py
anna_tasks/base/__init__.py
anna_tasks/base/config.py
anna_tasks/base/checkout/__init__.py
anna_tasks/base/checkout/cart/__init__.py
anna_tasks/base/checkout/cart/add.py
anna_tasks/base/checkout/cart/empty.py
anna_tasks/blaelefant/__init__.py
anna_tasks/blaelefant/config.py
anna_tasks/blaelefant/checkout/__init__.py
anna_tasks/blaelefant/checkout/cart/__init__.py
anna_tasks/blaelefant/checkout/cart/add.py
anna_tasks/blaelefant/checkout/cart/remove.py
anna_tasks/buildor/__init__.py
anna_tasks/buildor/config.py
anna_tasks/buildor/checkout/__init__.py
anna_tasks/buildor/checkout/cart/__init__.py
anna_tasks/buildor/checkout/cart/add.py
anna_tasks/buildor/checkout/cart/remove.py
anna_tasks/houseofmansson/__init__.py
anna_tasks/houseofmansson/config.py
anna_tasks/houseofmansson/checkout/__init__.py
anna_tasks/houseofmansson/checkout/cart/__init__.py
anna_tasks/houseofmansson/checkout/cart/add.py
anna_tasks/houseofmansson/checkout/cart/remove.py
anna_tasks/template23/__init__.py
anna_tasks/template23/config.py
anna_tasks/template23/checkout/__init__.py
anna_tasks/template23/checkout/cart/__init__.py
anna_tasks/template23/checkout/cart/add.py
anna_tasks/template23/checkout/cart/empty.py
anna_tasks/template23/checkout/order/__init__.py
anna_tasks/template23/checkout/order/place.py
anna_tasks-1.0.13.dist-info/METADATA
anna_tasks-1.0.13.dist-info/WHEEL
anna_tasks-1.0.13.dist-info/top_level.txt
anna_tasks-1.0.13.dist-info/RECORD
