Metadata-Version: 2.1
Name: anna-tasks
Version: 1.0.13
Summary: anna task package
Home-page: https://github.com/patrikpihlstrom/anna-tasks
Author: Patrik Pihlstrom
Author-email: patrik.pihlstrom@gmail.com
License: UNKNOWN
Platform: UNKNOWN
Requires-Dist: anna-lib
